ecrtools/__init__.py
ecrtools/main.py
ecrtools/commands/__init__.py
ecrtools/commands/images.py
ecrtools/commands/repos.py
ecrtools/lib/__init__.py
ecrtools/lib/ecr.py
ecrtools/lib/utils.py
ecrtools-0.0.7.dist-info/LICENSE
ecrtools-0.0.7.dist-info/METADATA
ecrtools-0.0.7.dist-info/WHEEL
ecrtools-0.0.7.dist-info/entry_points.txt
ecrtools-0.0.7.dist-info/top_level.txt
ecrtools-0.0.7.dist-info/RECORD
